README.txt
bootstrap.py
buildout.cfg
setup.py
src/zodict/__init__.py
src/zodict/_zodict.py
src/zodict/events.py
src/zodict/events.txt
src/zodict/interfaces.py
src/zodict/locking.py
src/zodict/locking.txt
src/zodict/node.py
src/zodict/node.txt
src/zodict.egg-info/PKG-INFO
src/zodict.egg-info/SOURCES.txt
src/zodict.egg-info/dependency_links.txt
src/zodict.egg-info/namespace_packages.txt
src/zodict.egg-info/requires.txt
src/zodict.egg-info/top_level.txt
src/zodict.egg-info/zip-safe
src/zodict/tests/__init__.py
src/zodict/tests/profiling.py
src/zodict/tests/test_zodict.py