Metadata-Version: 1.0
Name: zodict
Version: 1.9.3
Summary: zope.interface compliant ordered dictionary and zope.location aware node.
Home-page: https://svn.plone.org/svn/archetypes/AGX/zodict
Author: Robert Niederreiter
Author-email: dev@bluedynamics.com
License: Python Software Foundation License
Keywords: odict zodict tree node leaf datamodel container
Platform: UNKNOWN
Classifier: Development Status :: 5 - Production/Stable
Classifier: License :: OSI Approved :: Python Software Foundation License
Classifier: Framework :: Zope3
Classifier: Operating System :: OS Independent
Classifier: Programming Language :: Python
Classifier: Topic :: Software Development
